gasp/__init__.py
gasp/deserializable.py
gasp/gasp.cpython-312-darwin.so
gasp/gasp.pyi
gasp/jinja_helpers.py
gasp/template_helpers.py
gasp_py-1.3.6.dist-info/METADATA
gasp_py-1.3.6.dist-info/WHEEL
gasp_py-1.3.6.dist-info/licenses/LICENSE
gasp_py-1.3.6.dist-info/RECORD
