Metadata-Version: 2.4
Name: gasp-py
Version: 1.3.6
Classifier: Programming Language :: Rust
Classifier: Programming Language :: Python :: Implementation :: CPython
Classifier: Programming Language :: Python :: 3.7
Classifier: Programming Language :: Python :: 3.8
Classifier: Programming Language :: Python :: 3.9
Classifier: Programming Language :: Python :: 3.10
Classifier: Programming Language :: Python :: 3.11
Classifier: Programming Language :: Python :: 3.12
Classifier: Development Status :: 3 - Alpha
Classifier: Intended Audience :: Developers
Classifier: Topic :: Software Development :: Libraries :: Python Modules
Classifier: License :: OSI Approved :: Apache Software License
Requires-Dist: jinja2>=3.0.0
License-File: LICENSE
Summary: GASP (Gee Another Schema Parser) - A validator and type safe deserializer for LLM output.
Keywords: schema,validation,json,llm,prompt,parser,type-safe,deserializer
Author-email: Ian Butler <ian@bismuth.sh>
License: Apache-2.0
Requires-Python: >=3.7
Project-URL: Repository, https://github.com/iantbutler01/gasp
Project-URL: Documentation, https://github.com/iantbutler01/gasp#readme
